{
    "backend": "django",
    "db_name": "",
    "db_pass": "",
    "db_type": "sqlite",
    "db_user": "",
    "dbms": "1",
    "description": "generated product",
    "design": "soft-ui-dashboard",
    "docker": "1",
    "err_code": 0,
    "frontend": "",
    "heroku": "0",
    "pattern": "mvc",
    "pro": "0",
    "task_id": "6c3671e4-2142-41d6-b6bc-57442075b3c6",
    "task_info": "Upload Sources [0%] - 351 files",
    "task_output": "6c3671e4-2142-41d6-b6bc-57442075b3c6.zip",
    "task_result": "SUCCESS",
    "task_state": "RUNNING",
    "task_ts_end": "2025-02-01-13-36-26",
    "task_ts_start": "2025-02-01-13-36-23"
}